[
    {
        "id": "ws",
        "text": "Workspace",
        "children": [
            {
                "id": "last-open",
                "text": "Last open",
                "children": [
                    {
                        "text": "ProjectName_a.json"
                    }
                ],
                "type": "lo-setting",
                "order": 1,
                "a_attr":{"class":"nav-link"},
                "state": {
                    "opened": true
                }
            },
            {
                "id": "recent-open",
                "text": "Open recent",
                "children": [
                    "ProjectName_a.json",
                    "Project.json"
                ],
                "type": "ro-setting",
                "a_attr":{"class":"nav-link"},
                "order": 2
                
            }
        ],
        "li_attr" : { "class" : "nav-item has-treeview" },
        "a_attr":{"class":"nav-link"},
        "state": {
            "opened": true
        },
        "type": "#"
    }
]